displayctl/__init__.py
displayctl/__main__.py
displayctl/cli.py
displayctl-1.2.2.dist-info/METADATA
displayctl-1.2.2.dist-info/WHEEL
displayctl-1.2.2.dist-info/entry_points.txt
displayctl-1.2.2.dist-info/RECORD
