Metadata-Version: 2.4
Name: displayctl
Version: 1.2.2
Summary: Display Configuration Manager for GNOME
Project-URL: Homepage, https://github.com/sorenisanerd/displayctl
Project-URL: Repository, https://github.com/sorenisanerd/displayctl
Project-URL: Issues, https://github.com/sorenisanerd/displayctl/issues
Author: Soren L. Hansen
License: MIT
Classifier: Development Status :: 4 - Beta
Classifier: Environment :: X11 Applications :: Gnome
Classifier: Intended Audience :: End Users/Desktop
Classifier: License :: OSI Approved :: MIT License
Classifier: Operating System :: POSIX :: Linux
Classifier: Programming Language :: Python :: 3
Classifier: Programming Language :: Python :: 3.8
Classifier: Programming Language :: Python :: 3.9
Classifier: Programming Language :: Python :: 3.10
Classifier: Programming Language :: Python :: 3.11
Classifier: Programming Language :: Python :: 3.12
Classifier: Topic :: Desktop Environment
Classifier: Topic :: System :: Hardware
Classifier: Topic :: Utilities
Requires-Python: >=3.8
Requires-Dist: dbus-python; sys_platform == 'linux'
Provides-Extra: dev
Requires-Dist: build; extra == 'dev'
Requires-Dist: hatchling; extra == 'dev'
